{
    "AGN": 40, 
    "AGM": 39, 
    "AGK": 38, 
    "AGH": 37, 
    "AGG": 36, 
    "RYG": 493, 
    "AGC": 35, 
    "AGB": 34, 
    "AGA": 33, 
    "RYA": 491, 
    "AMG": 58, 
    "AGY": 45, 
    "AGW": 44, 
    "RYT": 494, 
    "AGT": 43, 
    "AGS": 42, 
    "AGR": 41, 
    "CGG": 144, 
    "TAT": 539, 
    "TAW": 540, 
    "KYM": 390, 
    "TAS": 538, 
    "KYC": 388, 
    "KYA": 387, 
    "KYG": 389, 
    "TAY": 541, 
    "KRG": 371, 
    "TAG": 533, 
    "TAA": 531, 
    "TAC": 532, 
    "KYR": 391, 
    "TAN": 536, 
    "KYT": 392, 
    "WRG": 664, 
    "WRC": 663, 
    "WRA": 662, 
    "RYC": 492, 
    "BYH": 115, 
    "WRY": 665, 
    "AHA": 46, 
    "AHG": 47, 
    "MAA": 393, 
    "MAC": 394, 
    "AHT": 48, 
    "TSK": 599, 
    "CMG": 163, 
    "TSG": 598, 
    "CMC": 162, 
    "TSC": 597, 
    "CMA": 161, 
    "TSA": 596, 
    "TSY": 601, 
    "CMW": 165, 
    "TST": 600, 
    "CMT": 164, 
    "CRT": 177, 
    "TTY": 615, 
    "GCG": 242, 
    "TTS": 611, 
    "TTR": 610, 
    "WCT": 648, 
    "TTW": 614, 
    "TTV": 613, 
    "TTT": 612, 
    "TTK": 607, 
    "TRA": 586, 
    "TTH": 606, 
    "TTN": 609, 
    "TTM": 608, 
    "TTC": 604, 
    "TTB": 603, 
    "TTA": 602, 
    "TTG": 605, 
    "CSG": 181, 
    "GRW": 295, 
    "GRT": 294, 
    "CYC": 209, 
    "GRR": 293, 
    "WGC": 650, 
    "CSA": 179, 
    "GRY": 296, 
    "GRG": 290, 
    "WGW": 653, 
    "GRC": 289, 
    "GRA": 288, 
    "GRM": 292, 
    "WGY": 654, 
    "GRK": 291, 
    "MAT": 396, 
    "CBA": 127, 
    "KKY": 366, 
    "TAR": 537, 
    "RWG": 487, 
    "KKW": 365, 
    "RWM": 488, 
    "RWR": 489, 
    "RWT": 490, 
    "NTG": 445, 
    "CBT": 128, 
    "KKG": 363, 
    "YTK": 724, 
    "CTT": 194, 
    "AKY": 55, 
    "CTW": 196, 
    "CTR": 192, 
    "CTS": 193, 
    "AKR": 53, 
    "SMS": 515, 
    "CTY": 197, 
    "AKT": 54, 
    "CTG": 188, 
    "CTA": 186, 
    "AKM": 52, 
    "CTC": 187, 
    "AKC": 50, 
    "CTM": 190, 
    "AKA": 49, 
    "AKG": 51, 
    "TRS": 592, 
    "CTK": 189, 
    "GGT": 261, 
    "GGW": 263, 
    "GGV": 262, 
    "GGS": 260, 
    "GGR": 259, 
    "GGY": 264, 
    "WHT": 655, 
    "GGG": 255, 
    "GGA": 252, 
    "GGC": 254, 
    "GGB": 253, 
    "GGM": 257, 
    "GGN": 258, 
    "GGK": 256, 
    "TAM": 535, 
    "HTC": 340, 
    "HTA": 339, 
    "MMT": 410, 
    "NTT": 447, 
    "NTN": 446, 
    "NTA": 443, 
    "MMG": 409, 
    "TAK": 534, 
    "MMC": 408, 
    "BAC": 106, 
    "CAY": 126, 
    "CAS": 123, 
    "CAR": 122, 
    "CAW": 125, 
    "BAT": 107, 
    "CAT": 124, 
    "CAK": 119, 
    "CAN": 121, 
    "CAM": 120, 
    "BAA": 105, 
    "CAC": 117, 
    "CAA": 116, 
    "CAG": 118, 
    "YTA": 721, 
    "STG": 523, 
    "KTY": 381, 
    "STC": 522, 
    "KTT": 380, 
    "STT": 524, 
    "KTM": 379, 
    "WCC": 646, 
    "ABT": 16, 
    "WCG": 647, 
    "HGG": 337, 
    "KTG": 378, 
    "STY": 525, 
    "KTC": 377, 
    "RSG": 480, 
    "NCT": 433, 
    "RSC": 479, 
    "NCN": 432, 
    "RST": 481, 
    "NCA": 429, 
    "NCC": 430, 
    "NCG": 431, 
    "YHK": 703, 
    "GHA": 265, 
    "RAG": 450, 
    "WTR": 671, 
    "WTT": 672, 
    "RAC": 449, 
    "RAA": 448, 
    "SAC": 496, 
    "WTY": 674, 
    "SAA": 495, 
    "SAG": 497, 
    "RAK": 451, 
    "RAW": 455, 
    "RAT": 454, 
    "WTC": 669, 
    "RAR": 452, 
    "RAS": 453, 
    "WTG": 670, 
    "RAY": 456, 
    "AYM": 100, 
    "CHA": 153, 
    "YMR": 711, 
    "YMT": 712, 
    "AYG": 99, 
    "AYA": 97, 
    "AYC": 98, 
    "YMA": 709, 
    "YMC": 710, 
    "AYY": 104, 
    "AYT": 102, 
    "AYW": 103, 
    "MRG": 412, 
    "AYR": 101, 
    "KAC": 344, 
    "TYM": 629, 
    "KAA": 343, 
    "KAG": 345, 
    "TYK": 628, 
    "TYG": 627, 
    "TYA": 625, 
    "KAM": 346, 
    "TYC": 626, 
    "KAR": 347, 
    "TYY": 633, 
    "KAT": 348, 
    "TYT": 631, 
    "WYC": 679, 
    "TYW": 632, 
    "TYR": 630, 
    "KST": 374, 
    "NGG": 436, 
    "NGA": 434, 
    "NGC": 435, 
    "NGN": 437, 
    "KSY": 375, 
    "NGT": 438, 
    "ABC": 15, 
    "YSS": 719, 
    "YSR": 718, 
    "KSK": 373, 
    "STA": 521, 
    "TKG": 571, 
    "RTG": 484, 
    "RTA": 482, 
    "TKC": 570, 
    "RTC": 483, 
    "TKA": 569, 
    "RTT": 485, 
    "TKT": 573, 
    "TKR": 572, 
    "RTY": 486, 
    "TKY": 575, 
    "GCA": 240, 
    "GCC": 241, 
    "MAG": 395, 
    "CSK": 182, 
    "YTY": 728, 
    "GCK": 243, 
    "YTT": 727, 
    "GCM": 244, 
    "YTS": 726, 
    "CSC": 180, 
    "GCN": 245, 
    "GCS": 247, 
    "GCR": 246, 
    "CSY": 185, 
    "GCT": 248, 
    "GCW": 249, 
    "GCY": 250, 
    "YTG": 723, 
    "YTC": 722, 
    "CSR": 183, 
    "MGC": 402, 
    "WCA": 645, 
    "MGA": 401, 
    "MGG": 403, 
    "SSM": 520, 
    "MGR": 404, 
    "BTG": 114, 
    "BTC": 113, 
    "MGT": 405, 
    "TBC": 542, 
    "SSC": 518, 
    "ATG": 80, 
    "WYT": 681, 
    "ATC": 79, 
    "ATA": 78, 
    "ATN": 83, 
    "ATM": 82, 
    "ATK": 81, 
    "WYY": 682, 
    "ATV": 87, 
    "ATW": 88, 
    "ATT": 86, 
    "ATR": 84, 
    "ATS": 85, 
    "WYA": 678, 
    "ATY": 89, 
    "ASS": 76, 
    "DGC": 222, 
    "DGA": 221, 
    "RMW": 473, 
    "RMT": 472, 
    "AST": 77, 
    "GBA": 237, 
    "KTA": 376, 
    "ASC": 74, 
    "RMC": 471, 
    "ASA": 73, 
    "ASG": 75, 
    "MRC": 411, 
    "HGA": 336, 
    "GTA": 303, 
    "GTC": 304, 
    "GTD": 305, 
    "GTG": 306, 
    "RCY": 461, 
    "YAT": 688, 
    "GTK": 307, 
    "GTM": 308, 
    "GTN": 309, 
    "YAR": 687, 
    "GTR": 310, 
    "GTS": 311, 
    "GTT": 312, 
    "GTV": 313, 
    "GTW": 314, 
    "GTY": 315, 
    "YAG": 685, 
    "YAA": 683, 
    "YAC": 684, 
    "CCK": 132, 
    "CGR": 148, 
    "CRC": 172, 
    "DMR": 223, 
    "CGT": 150, 
    "CRA": 171, 
    "YWW": 734, 
    "AAG": 4, 
    "YWT": 733, 
    "AAA": 1, 
    "YWR": 732, 
    "AAC": 3, 
    "AAB": 2, 
    "AAM": 7, 
    "AAN": 8, 
    "AAH": 5, 
    "AAK": 6, 
    "WBY": 644, 
    "YWG": 730, 
    "AAT": 11, 
    "AAW": 13, 
    "AAV": 12, 
    "YWA": 729, 
    "AAR": 9, 
    "AAY": 14, 
    "GYG": 327, 
    "CYR": 213, 
    "GYC": 326, 
    "TGW": 566, 
    "GYA": 325, 
    "CYT": 214, 
    "GYM": 328, 
    "TGY": 567, 
    "GYW": 332, 
    "TGC": 558, 
    "CYA": 208, 
    "GYT": 331, 
    "CYG": 210, 
    "GYR": 329, 
    "CYK": 211, 
    "TGK": 560, 
    "TGN": 562, 
    "GYY": 333, 
    "TGM": 561, 
    "CWY": 207, 
    "SSK": 519, 
    "CWR": 204, 
    "CWT": 205, 
    "CWW": 206, 
    "CWM": 203, 
    "CWA": 199, 
    "CWC": 201, 
    "CWB": 200, 
    "CWG": 202, 
    "MCG": 399, 
    "WKC": 657, 
    "MCC": 398, 
    "MCA": 397, 
    "MCT": 400, 
    "CKD": 156, 
    "CKG": 157, 
    "CKA": 154, 
    "YAK": 686, 
    "CKC": 155, 
    "ADA": 32, 
    "CKK": 158, 
    "CKT": 159, 
    "BGT": 112, 
    "CKY": 160, 
    "NTC": 444, 
    "GST": 301, 
    "AWY": 96, 
    "AWW": 95, 
    "AWT": 94, 
    "DCC": 219, 
    "DCA": 218, 
    "AWG": 93, 
    "DCT": 220, 
    "AWC": 92, 
    "AWA": 91, 
    "HAA": 334, 
    "CST": 184, 
    "THG": 568, 
    "KRA": 369, 
    "HAT": 335, 
    "SYC": 526, 
    "CCM": 133, 
    "SYG": 527, 
    "SYS": 529, 
    "SYR": 528, 
    "SYY": 530, 
    "CRR": 175, 
    "GBG": 239, 
    "SKW": 514, 
    "RGT": 467, 
    "GBC": 238, 
    "SKS": 513, 
    "RGW": 468, 
    "RKY": 470, 
    "CRY": 178, 
    "WGG": 651, 
    "RGA": 462, 
    "SKG": 511, 
    "RGC": 463, 
    "CRG": 173, 
    "RGG": 464, 
    "WGA": 649, 
    "RGK": 465, 
    "RGM": 466, 
    "SKK": 512, 
    "CRM": 174, 
    "TCY": 553, 
    "TCW": 552, 
    "TCT": 551, 
    "TCR": 549, 
    "TCS": 550, 
    "CGA": 142, 
    "TCN": 548, 
    "TCM": 547, 
    "TGA": 556, 
    "TCK": 546, 
    "TCG": 545, 
    "TCC": 544, 
    "TCA": 543, 
    "YKA": 704, 
    "GKR": 271, 
    "YKG": 705, 
    "GKS": 272, 
    "VGG": 637, 
    "GKT": 273, 
    "GKW": 274, 
    "VGA": 635, 
    "YKR": 706, 
    "GKK": 269, 
    "GKM": 270, 
    "YKT": 707, 
    "GKA": 266, 
    "GKC": 267, 
    "VGC": 636, 
    "GKG": 268, 
    "WWT": 677, 
    "ANG": 63, 
    "ANA": 61, 
    "WGT": 652, 
    "ANN": 64, 
    "WTW": 673, 
    "ANT": 65, 
    "WWG": 676, 
    "WWA": 675, 
    "WYG": 680, 
    "GWG": 319, 
    "GWA": 317, 
    "GWC": 318, 
    "BCG": 110, 
    "KMK": 367, 
    "GWH": 320, 
    "GWK": 321, 
    "BCC": 109, 
    "TMA": 576, 
    "KMT": 368, 
    "GWS": 322, 
    "TMG": 578, 
    "BCT": 111, 
    "GWY": 324, 
    "YKY": 708, 
    "KDM": 354, 
    "WTA": 668, 
    "TVG": 616, 
    "SRA": 516, 
    "WAG": 640, 
    "KRS": 372, 
    "YRC": 714, 
    "WAC": 639, 
    "WAA": 638, 
    "YRG": 715, 
    "SRR": 517, 
    "YWY": 735, 
    "WAW": 643, 
    "KRC": 370, 
    "WAT": 642, 
    "YRT": 716, 
    "WAR": 641, 
    "YYT": 741, 
    "YYW": 742, 
    "CDG": 141, 
    "YYS": 740, 
    "CDC": 140, 
    "ANC": 62, 
    "YYY": 743, 
    "YYG": 738, 
    "YYA": 736, 
    "YYC": 737, 
    "SAT": 498, 
    "TDW": 555, 
    "YYK": 739, 
    "MKG": 406, 
    "AAS": 10, 
    "GNT": 287, 
    "RCT": 460, 
    "MKK": 407, 
    "GNC": 284, 
    "WSS": 666, 
    "GNA": 283, 
    "GNG": 285, 
    "WSY": 667, 
    "CVG": 198, 
    "RCG": 459, 
    "GNN": 286, 
    "RCA": 457, 
    "RCC": 458, 
    "GAY": 236, 
    "GAW": 235, 
    "YWK": 731, 
    "GAT": 234, 
    "GAS": 233, 
    "GAR": 232, 
    "GAN": 231, 
    "GAM": 230, 
    "GAK": 229, 
    "GAG": 228, 
    "GAD": 227, 
    "GAC": 226, 
    "GAA": 225, 
    "TGR": 563, 
    "KKK": 364, 
    "TGS": 564, 
    "MTW": 418, 
    "MTT": 417, 
    "MTC": 415, 
    "MTA": 414, 
    "MTG": 416, 
    "ARR": 69, 
    "ART": 70, 
    "TGT": 565, 
    "ARW": 71, 
    "ARY": 72, 
    "ARA": 66, 
    "ARC": 67, 
    "ARG": 68, 
    "CYY": 216, 
    "NAC": 425, 
    "GSS": 300, 
    "NAA": 424, 
    "CCY": 139, 
    "NAG": 426, 
    "GSY": 302, 
    "CCT": 137, 
    "CCW": 138, 
    "NAN": 427, 
    "CTV": 195, 
    "CCS": 136, 
    "CCR": 135, 
    "GSA": 297, 
    "GSC": 298, 
    "CCN": 134, 
    "GSG": 299, 
    "TMT": 580, 
    "CCG": 131, 
    "CCA": 129, 
    "CCC": 130, 
    "TGB": 557, 
    "NNG": 441, 
    "HKS": 338, 
    "NNC": 440, 
    "MYT": 423, 
    "NNA": 439, 
    "KWR": 384, 
    "TRK": 589, 
    "GYS": 330, 
    "MYC": 422, 
    "NNT": 442, 
    "KWT": 385, 
    "BCA": 108, 
    "KWY": 386, 
    "WMM": 661, 
    "WMC": 660, 
    "WMA": 659, 
    "GWT": 323, 
    "TMC": 577, 
    "CYM": 212, 
    "MWS": 420, 
    "MWW": 421, 
    "MWA": 419, 
    "CTN": 191, 
    "KWA": 382, 
    "AMM": 59, 
    "SCK": 502, 
    "AMA": 56, 
    "AMC": 57, 
    "SCA": 499, 
    "SCC": 500, 
    "SCT": 503, 
    "SCW": 504, 
    "AMT": 60, 
    "TDG": 554, 
    "YCY": 695, 
    "VCK": 634, 
    "TRM": 590, 
    "YCS": 692, 
    "TRC": 587, 
    "YCW": 694, 
    "TRG": 588, 
    "YCT": 693, 
    "TRY": 595, 
    "YCC": 690, 
    "TKW": 574, 
    "YCA": 689, 
    "TRR": 591, 
    "YCG": 691, 
    "TRT": 593, 
    "TRW": 594, 
    "KCG": 351, 
    "HTD": 341, 
    "KCA": 349, 
    "KCC": 350, 
    "KCM": 352, 
    "CRS": 176, 
    "KCT": 353, 
    "HTT": 342, 
    "AVG": 90, 
    "ACC": 19, 
    "ACB": 18, 
    "ACA": 17, 
    "ACG": 21, 
    "ACD": 20, 
    "ACK": 23, 
    "NAT": 428, 
    "ACH": 22, 
    "ACN": 25, 
    "ACM": 24, 
    "ACS": 27, 
    "ACR": 26, 
    "ACW": 30, 
    "ACV": 29, 
    "ACT": 28, 
    "ACY": 31, 
    "CGK": 145, 
    "CGM": 146, 
    "CGN": 147, 
    "RRG": 476, 
    "CGC": 143, 
    "RRC": 475, 
    "RRA": 474, 
    "CGY": 152, 
    "CGS": 149, 
    "RRT": 478, 
    "RRR": 477, 
    "CGW": 151, 
    "GMK": 278, 
    "GMC": 276, 
    "YSG": 717, 
    "GMA": 275, 
    "GMG": 277, 
    "GMY": 282, 
    "KWG": 383, 
    "GMR": 279, 
    "CYW": 215, 
    "GMW": 281, 
    "GMT": 280, 
    "KGW": 361, 
    "WKA": 656, 
    "GDC": 251, 
    "TWC": 618, 
    "TWA": 617, 
    "YTR": 725, 
    "TWG": 619, 
    "TWK": 620, 
    "TWM": 621, 
    "TWR": 622, 
    "WKG": 658, 
    "TWT": 623, 
    "MSG": 413, 
    "TWY": 624, 
    "KGA": 355, 
    "SGR": 508, 
    "SGT": 509, 
    "SGW": 510, 
    "DAT": 217, 
    "RKA": 469, 
    "YRA": 713, 
    "SGA": 505, 
    "SGC": 506, 
    "YST": 720, 
    "SGG": 507, 
    "TNT": 585, 
    "CNT": 170, 
    "GVC": 316, 
    "CNG": 168, 
    "TNG": 583, 
    "TNA": 581, 
    "CNC": 167, 
    "TNC": 582, 
    "CNA": 166, 
    "CNN": 169, 
    "DWK": 224, 
    "TNN": 584, 
    "YGG": 698, 
    "KGS": 359, 
    "YGC": 697, 
    "KGT": 360, 
    "YGA": 696, 
    "KGY": 362, 
    "TMR": 579, 
    "YGK": 699, 
    "TGG": 559, 
    "KGC": 356, 
    "YGT": 702, 
    "YGS": 701, 
    "YGR": 700, 
    "KGG": 357, 
    "KGK": 358, 
    "SCG": 501
}